ott_platformm/__init__.py
ott_platformm/ott_platformm.py
ott_platformm-0.1.dist-info/License.txt
ott_platformm-0.1.dist-info/METADATA
ott_platformm-0.1.dist-info/WHEEL
ott_platformm-0.1.dist-info/top_level.txt
ott_platformm-0.1.dist-info/RECORD
