Metadata-Version: 2.1
Name: ott-platformm
Version: 0.1
Summary: API package that provides us the method to fetch the data from the API, along with the method to convert that into proper dataframe
Author: ishita
Author-email: ishitagupta1012@email.com
License: MIT
License-File: License.txt
Requires-Dist: pandas
Requires-Dist: requests
